{"authorDailyContributionsMap":{"SwaminathanViswa":[{"date":"2024-08-21","commitResults":[{"hash":"fea45c016c5b84edc476be3aae721ff5a5c3b1a4","isMergeCommit":false,"messageTitle":"Changed from DUKE to BitBot","messageBody":"","fileTypesAndContributionMap":{"java":{"insertions":0,"deletions":0}}},{"hash":"e1b25f11dd8932851e09f508fa4dfebc9276fa01","isMergeCommit":false,"messageTitle":"changed DUKE to BitBot","messageBody":"","fileTypesAndContributionMap":{"java":{"insertions":11,"deletions":7}}},{"hash":"6728f10413c4edc900cdac9aed9dea9617e91e17","isMergeCommit":false,"messageTitle":"added the scanner to read user input","messageBody":"","fileTypesAndContributionMap":{"java":{"insertions":23,"deletions":8}}},{"hash":"2cd529b90e05ef0698775906d901713f18758131","isMergeCommit":false,"messageTitle":"added the ArrayList to store events","messageBody":"","fileTypesAndContributionMap":{"java":{"insertions":29,"deletions":5}}},{"hash":"455bb296af009d506d5b0fc78348149862889b5e","isMergeCommit":false,"messageTitle":"added the mark as done component","messageBody":"","fileTypesAndContributionMap":{"java":{"insertions":85,"deletions":10}}}]},{"date":"2024-08-22","commitResults":[{"hash":"528512b57ceb437c51b85c78349e722c120738c7","isMergeCommit":false,"messageTitle":"added the toDos, events and deadlines","messageBody":"","fileTypesAndContributionMap":{"java":{"insertions":170,"deletions":11}}},{"hash":"37c97819a074d34330fa7845d26b51811e3b873b","isMergeCommit":false,"messageTitle":"added test cases and inputs for testing","messageBody":"","fileTypesAndContributionMap":{"txt":{"insertions":2,"deletions":0},"java":{"insertions":0,"deletions":2},"bat":{"insertions":1,"deletions":1}}},{"hash":"f740c148ff20c38a0a4820d04c9019f15a0268d4","isMergeCommit":false,"messageTitle":"added exception handling","messageBody":"","fileTypesAndContributionMap":{"java":{"insertions":207,"deletions":152}}},{"hash":"ff62bf09b0cb863fa8b95f49c954e349860110ac","isMergeCommit":false,"messageTitle":"added delete functionality","messageBody":"","fileTypesAndContributionMap":{"java":{"insertions":18,"deletions":16}}}]}]},"authorFileTypeContributionMap":{"SwaminathanViswa":{"java":340,"md":0,"fxml":0,"sh":0,"bat":1,"gradle":0,"txt":2}},"authorContributionVariance":{"SwaminathanViswa":40857.633},"authorDisplayNameMap":{"SwaminathanViswa":"SWAM..ISWA"}}
